MANIFEST.in
README.rst
setup.py
openvpn_manager/__init__.py
openvpn_manager/test_api.py
openvpn_manager.egg-info/PKG-INFO
openvpn_manager.egg-info/SOURCES.txt
openvpn_manager.egg-info/dependency_links.txt
openvpn_manager.egg-info/requires.txt
openvpn_manager.egg-info/top_level.txt
openvpn_manager/api/__init__.py
openvpn_manager/api/app.py
openvpn_manager/api/wsgi.py
openvpn_manager/cli/__init__.py
openvpn_manager/cli/poller.py
openvpn_manager/docs/config.json.sample
openvpn_manager/docs/httpd.conf.sample
openvpn_manager/docs/initd-api.sh
openvpn_manager/docs/initd-poller.sh