Metadata-Version: 1.1
Name: openvpn-manager
Version: 1.0.0.dev6
Summary: A simple OpenVPN Manager
Home-page: https://github.com/pgmillon/openvpn-manager
Author: Pierre-Gildas MILLON
Author-email: pg.millon@gmail.com
License: MIT
Keywords: openvpn manager
Platform: UNKNOWN
Classifier: Development Status :: 3 - Alpha
Classifier: Intended Audience :: Developers
Classifier: Topic :: System :: Networking
Classifier: License :: OSI Approved :: MIT License
Classifier: Programming Language :: Python :: 2.7
